lionabc/__init__.py
lionabc/characteristic.py
lionabc/concept.py
lionabc/exceptions.py
lionabc/observation.py
lionabc/observer.py
lionabc/record.py
lionabc/space.py
lionabc/version.py
lionabc-1.2.2.dist-info/LICENSE
lionabc-1.2.2.dist-info/METADATA
lionabc-1.2.2.dist-info/WHEEL
lionabc-1.2.2.dist-info/RECORD
