Metadata-Version: 2.1
Name: lionabc
Version: 1.2.2
Summary: 
Author: OceanLi
Author-email: 122793010+ohdearquant@users.noreply.github.com
Requires-Python: >=3.10,<4.0
Classifier: Programming Language :: Python :: 3
Classifier: Programming Language :: Python :: 3.10
Classifier: Programming Language :: Python :: 3.11
Classifier: Programming Language :: Python :: 3.12
